{
  "UserAgent": "MobileHub/1.0",
  "Version": "1.0",
  "CredentialsProvider": {
    "CognitoIdentity": {
      "Default": {
        "PoolId": "us-east-1:33fd9a6c-a616-4186-84f9-d72210150798",
        "Region": "us-east-1"
      }
    }
  },
  "IdentityManager": {
    "Default": {}
  },
  "PinpointAnalytics": {
    "Default": {
      "AppId": "842d8e3b11314d47806d4e140064bbc6",
      "Region": "us-east-1"
    }
  },
  "PinpointTargeting": {
    "Default": {
      "Region": "us-east-1"
    }
  }
}